__init__.py
fftLoss.py
fftloss-0.0.1.dist-info/licenses/LICENSE
fftloss-0.0.1.dist-info/METADATA
fftloss-0.0.1.dist-info/WHEEL
fftloss-0.0.1.dist-info/top_level.txt
fftloss-0.0.1.dist-info/RECORD
