Metadata-Version: 2.4
Name: fftLoss
Version: 0.0.1
Summary: The fftLoss @PyTorch is a frequency domain loss function that prevents the problem of weak frequency components being suppressed by strong frequency components when using a regular loss function. 
Author-email: Psyche Halo <Psyche@WinsGod.com>
Project-URL: Homepage, https://github.com/PsycheHalo/fftLoss
Project-URL: Issues, https://github.com/PsycheHalo/fftLoss/issues
Keywords: fftLoss,Loss,PyTorch,AI,neural,NN,FFT
Classifier: Programming Language :: Python :: 3
Classifier: Operating System :: OS Independent
Requires-Python: >=3.8
License-File: LICENSE
Requires-Dist: torch>=1.7.0
Dynamic: license-file
